{"name":"portalapi.github.io","tagline":"portalapi.com","body":"# portalapi.com\r\n\r\nImplementer of sanity in fast-paced chaos. Pleasant, cheerful and competent in a sea of snark. Currently, I'm at Acquia helping new customers get comfortable and get what they need to get started. I help technologists think about what they're doing, and help explain it to clients in ways that they like hearing. \r\n\r\nI've written and presented on project management since 2009. I still like it. \r\n \r\n## Testimonials:\r\n\r\n### Or really just overheard's from people I work with. \r\n \"Have I ever mentioned that \"portalapi\" sounds like a harry potter spell. It would cause nimrods to suddenly know what the f they're supposed to be doing.\" \r\n \"These clients are Hobbits. You are a Ranger and you have just led them through the wilderness.\"\r\n\r\n### The Real Reason you were here\r\n\r\n","google":"","note":"Don't delete this file! It's used internally to help with page regeneration."}
